odoo10_addon_donation_stay-10.0.1.0.0-py2.7-nspkg.pth
odoo/addons/donation_stay/README.rst
odoo/addons/donation_stay/__init__.py
odoo/addons/donation_stay/__manifest__.py
odoo/addons/donation_stay/donation_stay_data.xml
odoo/addons/donation_stay/stay_view.xml
odoo/addons/donation_stay/i18n/donation_stay.pot
odoo/addons/donation_stay/i18n/fr.po
odoo/addons/donation_stay/static/description/icon.png
odoo/addons/donation_stay/tests/__init__.py
odoo/addons/donation_stay/tests/test_donate_from_stay.py
odoo/addons/donation_stay/wizard/__init__.py
odoo/addons/donation_stay/wizard/create_donation_stay.py
odoo/addons/donation_stay/wizard/create_donation_stay_view.xml
odoo10_addon_donation_stay-10.0.1.0.0.dist-info/DESCRIPTION.rst
odoo10_addon_donation_stay-10.0.1.0.0.dist-info/METADATA
odoo10_addon_donation_stay-10.0.1.0.0.dist-info/RECORD
odoo10_addon_donation_stay-10.0.1.0.0.dist-info/WHEEL
odoo10_addon_donation_stay-10.0.1.0.0.dist-info/metadata.json
odoo10_addon_donation_stay-10.0.1.0.0.dist-info/namespace_packages.txt
odoo10_addon_donation_stay-10.0.1.0.0.dist-info/top_level.txt
